mongoman
