Metadata-Version: 1.0
Name: mongoman
Version: 0.2.2
Summary: PyMongo wrapper that provides ORM and easy MongoDB connection handling.
Home-page: https://github.com/ramazanpolat/mongoman
Author: Ramazan Polat
Author-email: ramazanpolat@gmail.com
License: MIT
Platform: UNKNOWN
